stactools/goes_glm/__init__.py
stactools/goes_glm/commands.py
stactools/goes_glm/constants.py
stactools/goes_glm/netcdf.py
stactools/goes_glm/parquet.py
stactools/goes_glm/stac.py
stactools_goes_glm-0.2.4.dist-info/licenses/LICENSE
stactools_goes_glm-0.2.4.dist-info/METADATA
stactools_goes_glm-0.2.4.dist-info/WHEEL
stactools_goes_glm-0.2.4.dist-info/top_level.txt
stactools_goes_glm-0.2.4.dist-info/RECORD
