Metadata-Version: 2.4
Name: stactools-goes-glm
Version: 0.2.4
Summary: stactools package for the Geostationary Lightning Mapper (GLM) on the GOES-16/R, GOES-17/S, and GOES-18/T satellites.
Home-page: https://github.com/stactools-packages/goes-glm
Author: Matthias Mohr
Author-email: matthias.mohr@radiant.earth
Project-URL: Issues, https://github.com/stactools-packages/goes-glm/issues
Keywords: stactools,goes,glm,lightning,STAC
Classifier: Development Status :: 4 - Beta
Classifier: License :: OSI Approved :: Apache Software License
Classifier: Programming Language :: Python :: 3.9
Classifier: Programming Language :: Python :: 3.10
Classifier: Programming Language :: Python :: 3.11
Classifier: Programming Language :: Python :: 3.12
Classifier: Programming Language :: Python :: 3.13
License-File: LICENSE
Requires-Dist: stactools>=0.4.0
Requires-Dist: python-dateutil>=2.7.0
Requires-Dist: types-python-dateutil>=2.7.0
Requires-Dist: netCDF4>=1.6.0
Requires-Dist: geopandas>=0.11.1
Requires-Dist: pyarrow>=8.0.0
Requires-Dist: shapely>=1.8.2
Requires-Dist: pystac<1.12
Dynamic: license-file
